LICENSE.txt
MANIFEST.in
PyAsyncScheduler.py
README.md
pyproject.toml
requirements.txt
setup.cfg
setup.py
PyAsyncScheduler.egg-info/PKG-INFO
PyAsyncScheduler.egg-info/SOURCES.txt
PyAsyncScheduler.egg-info/dependency_links.txt
PyAsyncScheduler.egg-info/entry_points.txt
PyAsyncScheduler.egg-info/top_level.txt