Metadata-Version: 2.2
Name: PyAsyncScheduler
Version: 0.0.1
Summary: An asynchronous task scheduler, with cron syntax, intervals, limits, dynamic configuration, and optional vault integration.
Home-page: https://github.com/mauricelambert/PyAsyncScheduler
Author: Maurice Lambert
Author-email: Maurice Lambert <mauricelambert434@gmail.com>
Maintainer: Maurice Lambert
Maintainer-email: Maurice Lambert <mauricelambert434@gmail.com>
License: GPL-3.0 License
Project-URL: Github, https://github.com/mauricelambert/PyAsyncScheduler
Project-URL: Documentation, https://mauricelambert.github.io/info/python/code/PyAsyncScheduler.html
Keywords: scheduler,cron,async,task-scheduler,background-tasks,vault
Platform: Windows
Platform: Linux
Platform: MacOS
Classifier: Topic :: System
Classifier: Environment :: Console
Classifier: Topic :: System :: Shells
Classifier: Operating System :: POSIX
Classifier: Natural Language :: English
Classifier: Programming Language :: Python
Classifier: Intended Audience :: Developers
Classifier: Topic :: System :: System Shells
Classifier: Operating System :: MacOS :: MacOS X
Classifier: Programming Language :: Python :: 3.8
Classifier: Operating System :: Microsoft :: Windows
Classifier: Topic :: System :: Systems Administration
Classifier: Topic :: Software Development :: Libraries
Classifier: Intended Audience :: System Administrators
Classifier: Development Status :: 5 - Production/Stable
Classifier: License :: OSI Approved :: GNU General Public License v3 or later (GPLv3+)
Requires-Python: >=3.8
License-File: LICENSE.txt
Dynamic: author
Dynamic: home-page
Dynamic: maintainer
Dynamic: requires-python
